MANIFEST.in
README.md
setup.py
chariot_plugin.egg-info/PKG-INFO
chariot_plugin.egg-info/SOURCES.txt
chariot_plugin.egg-info/dependency_links.txt
chariot_plugin.egg-info/entry_points.txt
chariot_plugin.egg-info/requires.txt
chariot_plugin.egg-info/top_level.txt
core/__init__.py
core/config.py
core/main.py
core/tasks.py
core/tools.py
core/res/__init__.py
core/res/demo.tar.gz
core/res/SDK/__init__.py
core/res/SDK/base.py
core/res/SDK/chariot.py
core/res/SDK/cli.py
core/res/SDK/models.py
core/res/SDK/plugin.py
core/res/SDK/subassembly.py
core/res/SDK/web.py