Metadata-Version: 2.1
Name: chariot-plugin
Version: 1.1.6
Summary: 插件生成等功能...
Home-page: https://www.chariots.cn/market/introduction
Author: andy
Author-email: 1472942893@qq.com
License: MIT
Platform: UNKNOWN
Requires-Python: >=3
